tocoli/__init__.py
tocoli/auth.py
tocoli/cmp.py
tocoli/enc.py
tocoli/filter.py
tocoli/fn.py
tocoli/join.py
tocoli/map.py
tocoli/ratio.py
tocoli/regex.py
tocoli/sort.py
tocoli/spell.py
tocoli/test.py
tocoli/type.py
tocoli/dsl/__init__.py
tocoli/dsl/filter.py
tocoli/dsl/join.py
tocoli/dsl/map.py
tocoli/dsl/sort.py
tocoli/dsl/string.py
tocoli/py2/__init__.py
tocoli/py2/enc.py
tocoli/py3/__init__.py
tocoli/py3/enc.py
tocolib-0.3.1.dist-info/LICENSE
tocolib-0.3.1.dist-info/METADATA
tocolib-0.3.1.dist-info/WHEEL
tocolib-0.3.1.dist-info/top_level.txt
tocolib-0.3.1.dist-info/RECORD
