Metadata-Version: 2.1
Name: tocolib
Version: 0.3.1
Summary: A utility library
Home-page: https://github.com/tocoli/tocolib
Author: Sebastian Wiesendahl
Author-email: sebastian@wiesendahl.de
License: MIT
Keywords: development utility library encoding sort filter testing
Platform: UNKNOWN
Classifier: Development Status :: 4 - Beta
Classifier: Intended Audience :: Developers
Classifier: Topic :: Utilities
Classifier: Topic :: Software Development :: Libraries
Classifier: Topic :: Software Development :: Localization
Classifier: Topic :: Software Development :: Internationalization
Classifier: Topic :: Software Development :: Testing
Classifier: Topic :: System :: Benchmark
Classifier: License :: OSI Approved :: MIT License
Classifier: Programming Language :: Python :: 2
Classifier: Programming Language :: Python :: 2.6
Classifier: Programming Language :: Python :: 2.7
Classifier: Programming Language :: Python :: 3
Classifier: Programming Language :: Python :: 3.2
Classifier: Programming Language :: Python :: 3.3
Classifier: Programming Language :: Python :: 3.4
Classifier: Programming Language :: Python :: 3.5
Classifier: Programming Language :: Python :: 3.6
Requires-Dist: six
Requires-Dist: chardet
Requires-Dist: python-levenshtein
Requires-Dist: itsdangerous
Requires-Dist: passlib (>=1.7.0)
